kindness/__init__.py
kindness/core.py
kindness-0.1.0.dist-info/LICENSE
kindness-0.1.0.dist-info/METADATA
kindness-0.1.0.dist-info/WHEEL
kindness-0.1.0.dist-info/top_level.txt
kindness-0.1.0.dist-info/RECORD
