Metadata-Version: 2.1
Name: kindness
Version: 0.1.0
Summary: A package to promote kindness through random acts, gratitude, and compliments
Home-page: https://github.com/mrnithesh/kindness
Author: mrnithesh
Author-email: mr.nithesh.k@gmail.com
Classifier: Programming Language :: Python :: 3
Classifier: License :: OSI Approved :: MIT License
Classifier: Operating System :: OS Independent
Requires-Python: >=3.6
License-File: LICENSE
